{
  "project_info": {
    "project_number": "39971107365",
    "firebase_url": "https://flutter-instagram-clone-8ec1a.firebaseio.com",
    "project_id": "flutter-instagram-clone-8ec1a",
    "storage_bucket": "flutter-instagram-clone-8ec1a.appspot.com"
  },
  "client": [
    {
      "client_info": {
        "mobilesdk_app_id": "1:39971107365:android:1dd9742d41c6e0b3aa45cc",
        "android_client_info": {
          "package_name": "com.example.instagramClone"
        }
      },
      "oauth_client": [
        {
          "client_id": "39971107365-0csv1435mm7gs9vv7ffe4qhmeg6rrr6j.apps.googleusercontent.com",
          "client_type": 3
        }
      ],
      "api_key": [
        {
          "current_key": "AIzaSyCWcMX7wt2fasGAfIor13xzhcxQqguSFHo"
        }
      ],
      "services": {
        "appinvite_service": {
          "other_platform_oauth_client": [
            {
              "client_id": "39971107365-0csv1435mm7gs9vv7ffe4qhmeg6rrr6j.apps.googleusercontent.com",
              "client_type": 3
            },
            {
              "client_id": "39971107365-q34c2bvli8tekeuf80anlnltujrl5tgn.apps.googleusercontent.com",
              "client_type": 2,
              "ios_info": {
                "bundle_id": "com.example.instagramClone"
              }
            }
          ]
        }
      }
    }
  ],
  "configuration_version": "1"
}